lboxd/__init__.py
lboxd/__main__.py
lboxd/lboxd.py
lboxd/utils.py
lboxd-1.2.1.dist-info/entry_points.txt
lboxd-1.2.1.dist-info/LICENSE
lboxd-1.2.1.dist-info/WHEEL
lboxd-1.2.1.dist-info/METADATA
lboxd-1.2.1.dist-info/RECORD
