Metadata-Version: 2.1
Name: lboxd
Version: 1.2.1
Summary: Letterboxd user tools.
License: MIT
Author: Your Name
Author-email: berkshiremind@.com
Requires-Python: >=3.8.5,<4.0.0
Classifier: License :: OSI Approved :: MIT License
Classifier: Programming Language :: Python :: 3
Requires-Dist: bs4 (>=0.0.1,<0.0.2)
Requires-Dist: requests (>=2.0.0,<3.0.0)
Requires-Dist: rich (>=9.6.1,<10.0.0)
